nlpchat/__init__.py
nlpchat/nlpchat.py
nlpchat-3.0.dist-info/LICENSE
nlpchat-3.0.dist-info/METADATA
nlpchat-3.0.dist-info/WHEEL
nlpchat-3.0.dist-info/top_level.txt
nlpchat-3.0.dist-info/RECORD
