Metadata-Version: 2.1
Name: nlpchat
Version: 3.0
Summary: A package to simplify chatbot creation using NLP.
Home-page: https://github.com/IMApurbo/nlpchat
Author: AKM Korishee Apurbo
Author-email: bandinvisible8@gmail.com
Classifier: Programming Language :: Python :: 3
Classifier: License :: OSI Approved :: MIT License
Classifier: Operating System :: OS Independent
Requires-Python: >=3.6
License-File: LICENSE
Requires-Dist: sentence-transformers
Requires-Dist: scikit-learn
Requires-Dist: numpy
Requires-Dist: pickle-mixin
